alcli/__init__.py
alcli/alertlogic_cli.py
alcli/argparser.py
alcli/arguments.py
alcli/clihelp.py
alcli/cliparser.py
alcli/version.py
alcli-1.0.70.dist-info/AUTHORS.rst
alcli-1.0.70.dist-info/LICENSE
alcli-1.0.70.dist-info/METADATA
alcli-1.0.70.dist-info/WHEEL
alcli-1.0.70.dist-info/entry_points.txt
alcli-1.0.70.dist-info/top_level.txt
alcli-1.0.70.dist-info/RECORD
