Metadata-Version: 2.1
Name: alcli
Version: 1.0.70
Summary: The Alert Logic Command Line Utility (CLI).
Home-page: https://github.com/alertlogic/alcli
Author: Alert Logic Inc.
Author-email: devsupport@alertlogic.com
License: MIT license
Keywords: alcli,almdr,alertlogic,alertlogic-cli
Platform: any
Classifier: Development Status :: 3 - Alpha
Classifier: Intended Audience :: Developers
Classifier: License :: OSI Approved :: MIT License
Classifier: Natural Language :: English
Classifier: Programming Language :: Python :: 3.7
Classifier: Programming Language :: Python :: 3.8
Requires-Python: >=3.7
License-File: LICENSE
License-File: AUTHORS.rst
Requires-Dist: alertlogic-sdk-python>=1.0.74
Requires-Dist: configparser==4.0.2
Requires-Dist: pyyaml>=5.4
Requires-Dist: jmespath==0.9.5
Requires-Dist: importlib-metadata==1.6.0
Provides-Extra: dev
Requires-Dist: pytest>=3; extra == "dev"
Requires-Dist: mock>=2.0.0; extra == "dev"
Requires-Dist: httpretty>=0.8.14; extra == "dev"
Requires-Dist: pycodestyle>=2.3.1; extra == "dev"
